ultracalc/__init__.py
ultracalc/core.py
ultracalc-1.0.1.dist-info/licenses/LICENSE
ultracalc-1.0.1.dist-info/METADATA
ultracalc-1.0.1.dist-info/WHEEL
ultracalc-1.0.1.dist-info/top_level.txt
ultracalc-1.0.1.dist-info/RECORD
