Metadata-Version: 2.4
Name: ultracalc
Version: 1.0.1
Summary: Infinite-precision calculator with math expression parsing
Author: kkyian
License: MIT
Classifier: Programming Language :: Python :: 3
Classifier: Operating System :: OS Independent
Requires-Python: >=3.7
License-File: LICENSE
Dynamic: author
Dynamic: classifier
Dynamic: license
Dynamic: license-file
Dynamic: requires-python
Dynamic: summary
